{
    "hostname": "gus",
    "log_level": "DEBUG",
    "db_name": "gus",

    "MistBuddy_PID_config": {
        "name": "mistbuddy",
        "setpoint": 1.0,
        "Kp": 92.4,
        "Ki": 30.8,
        "Kd": 23.1,
        "output_limits": [0, 10],
        "integral_limits":[0, 4],
        "tune_increment": 0,
        "comparison_function": "less_than",
        "mqtt": ["cmnd/mistbuddy_fan/POWER","cmnd/mistbuddy_mister/POWER"],
        "incoming_udp_port": 8094,
        "tune_udp_port": 9094,
        "telegraf_fieldname": "vpd_mean",
        "num_bias_seconds_on": 0
    },

    "StomaBuddy_PID_config": {
        "name": "stomabuddy",
        "setpoint": 1000,
        "Kp": 0.01,
        "Ki":0.0,
        "Kd":0.0,
        "output_limits": [0, 19],
        "integral_limits":[0, 2],
        "tune_increment": 0,
        "comparison_function": "greater_than",
        "mqtt": ["cmnd/stomabuddy/POWER"],
        "incoming_udp_port": 8095,
        "tune_udp_port": 9094,
        "telegraf_fieldname": "co2_mean",
        "num_bias_seconds_on": 0
    }
}